[
  { "airport_code": "DEL", "airport_name": "Indira Gandhi International Airport", "city": "Delhi", "gate_no": 10 },
  { "airport_code": "BOM", "airport_name": "Chhatrapati Shivaji Maharaj International Airport", "city": "Mumbai", "gate_no": 12 },
  { "airport_code": "BLR", "airport_name": "Kempegowda International Airport", "city": "Bengaluru", "gate_no": 16 },
  { "airport_code": "MAA", "airport_name": "Chennai International Airport", "city": "Chennai", "gate_no": 4 },
  { "airport_code": "HYD", "airport_name": "Rajiv Gandhi International Airport", "city": "Hyderabad", "gate_no": 7 },
  { "airport_code": "CCU", "airport_name": "Netaji Subhas Chandra Bose International Airport", "city": "Kolkata", "gate_no": 15 },
  { "airport_code": "AMD", "airport_name": "Sardar Vallabhbhai Patel International Airport", "city": "Ahmedabad", "gate_no": 8 },
  { "airport_code": "GOI", "airport_name": "Goa International Airport", "city": "Goa", "gate_no": 5 },
  { "airport_code": "PNQ", "airport_name": "Pune Airport", "city": "Pune", "gate_no": 9 },
  { "airport_code": "LKO", "airport_name": "Chaudhary Charan Singh Airport", "city": "Lucknow", "gate_no": 14 },
  { "airport_code": "VNS", "airport_name": "Lal Bahadur Shastri Airport", "city": "Varanasi", "gate_no": 18 },
  { "airport_code": "TRV", "airport_name": "Trivandrum International Airport", "city": "Thiruvananthapuram", "gate_no": 11 },
  { "airport_code": "COK", "airport_name": "Cochin International Airport", "city": "Kochi", "gate_no": 17 },
  { "airport_code": "IXC", "airport_name": "Chandigarh Airport", "city": "Chandigarh", "gate_no": 6 },
  { "airport_code": "ATQ", "airport_name": "Sri Guru Ram Dass Jee International Airport", "city": "Amritsar", "gate_no": 22 },
  { "airport_code": "BDQ", "airport_name": "Vadodara Airport", "city": "Vadodara", "gate_no": 7 },
  { "airport_code": "BHO", "airport_name": "Raja Bhoj Airport", "city": "Bhopal", "gate_no": 11 },
  { "airport_code": "BHU", "airport_name": "Bhavnagar Airport", "city": "Bhavnagar", "gate_no": 9 },
  { "airport_code": "BKB", "airport_name": "Nal Airport", "city": "Bikaner", "gate_no": 13 },
  { "airport_code": "BUP", "airport_name": "Bathinda Airport", "city": "Bathinda", "gate_no": 10 },
  { "airport_code": "DIB", "airport_name": "Dibrugarh Airport", "city": "Dibrugarh", "gate_no": 20 },
  { "airport_code": "GAU", "airport_name": "Lokpriya Gopinath Bordoloi International Airport", "city": "Guwahati", "gate_no": 19 },
  { "airport_code": "GAY", "airport_name": "Gaya Airport", "city": "Gaya", "gate_no": 8 },
  { "airport_code": "GWL", "airport_name": "Gwalior Airport", "city": "Gwalior", "gate_no": 9 },
  { "airport_code": "HBX", "airport_name": "Belgaum Airport", "city": "Belgaum", "gate_no": 4 },
  { "airport_code": "HSS", "airport_name": "Hissar Airport", "city": "Hisar", "gate_no": 12 },
  { "airport_code": "IMF", "airport_name": "Imphal Airport", "city": "Imphal", "gate_no": 14 },
  { "airport_code": "IXA", "airport_name": "Agartala Airport", "city": "Agartala", "gate_no": 8 },
  { "airport_code": "IXB", "airport_name": "Bagdogra Airport", "city": "Bagdogra", "gate_no": 15 },
  { "airport_code": "IXE", "airport_name": "Mangalore International Airport", "city": "Mangalore", "gate_no": 10 },
  { "airport_code": "IXG", "airport_name": "Belagavi Airport", "city": "Belagavi", "gate_no": 5 },
  { "airport_code": "IXJ", "airport_name": "Satwari Airport", "city": "Jammu", "gate_no": 16 },
  { "airport_code": "IXL", "airport_name": "Kushok Bakula Rimpochee Airport", "city": "Leh", "gate_no": 18 },
  { "airport_code": "IXM", "airport_name": "Madurai Airport", "city": "Madurai", "gate_no": 7 },
  { "airport_code": "IXR", "airport_name": "Birsa Munda Airport", "city": "Ranchi", "gate_no": 13 },
  { "airport_code": "IXU", "airport_name": "Aurangabad Airport", "city": "Aurangabad", "gate_no": 12 },
  { "airport_code": "IXZ", "airport_name": "Veer Savarkar International Airport", "city": "Port Blair", "gate_no": 14 },
  { "airport_code": "JAI", "airport_name": "Jaipur International Airport", "city": "Jaipur", "gate_no": 10 },
  { "airport_code": "JDH", "airport_name": "Jodhpur Airport", "city": "Jodhpur", "gate_no": 8 },
  { "airport_code": "JGA", "airport_name": "Jamnagar Airport", "city": "Jamnagar", "gate_no": 6 },
  { "airport_code": "JLR", "airport_name": "Jabalpur Airport", "city": "Jabalpur", "gate_no": 5 },
  { "airport_code": "JSA", "airport_name": "Jaisalmer Airport", "city": "Jaisalmer", "gate_no": 6 },
  { "airport_code": "KNU", "airport_name": "Kanpur Airport", "city": "Kanpur", "gate_no": 9 },
  { "airport_code": "KQH", "airport_name": "Kishangarh Airport", "city": "Ajmer", "gate_no": 12 },
  { "airport_code": "KUU", "airport_name": "Kullu-Manali Airport", "city": "Kullu", "gate_no": 11 },
  { "airport_code": "LDA", "airport_name": "Lakshadweep Airport", "city": "Lakshadweep", "gate_no": 3 },
  { "airport_code": "LGB", "airport_name": "Lilabari Airport", "city": "North Lakhimpur", "gate_no": 2 },
  { "airport_code": "MBD", "airport_name": "Moradabad Airport", "city": "Moradabad", "gate_no": 6 },
  { "airport_code": "MZU", "airport_name": "Lengpui Airport", "city": "Aizawl", "gate_no": 8 },
  { "airport_code": "NAG", "airport_name": "Dr. Babasaheb Ambedkar International Airport", "city": "Nagpur", "gate_no": 14 },
  { "airport_code": "PAT", "airport_name": "Jay Prakash Narayan Airport", "city": "Patna", "gate_no": 18 },
  { "airport_code": "RJA", "airport_name": "Rajahmundry Airport", "city": "Rajahmundry", "gate_no": 16 },
  { "airport_code": "RNC", "airport_name": "Ranchi 2 Airport", "city": "Ranchi", "gate_no": 13 },
  { "airport_code": "RPR", "airport_name": "Swami Vivekananda Airport", "city": "Raipur", "gate_no": 15 },
  { "airport_code": "SAG", "airport_name": "Sagar Airport", "city": "Sagar", "gate_no": 6 },
  { "airport_code": "SVD", "airport_name": "Silvassa Airport", "city": "Silvassa", "gate_no": 5 },
  { "airport_code": "SMF", "airport_name": "Sangli Airport", "city": "Sangli", "gate_no": 11 },
  { "airport_code": "SSE", "airport_name": "Solapur Airport", "city": "Solapur", "gate_no": 8 },
  { "airport_code": "SXR", "airport_name": "Sheikh ul-Alam International Airport", "city": "Srinagar", "gate_no": 17 },
  { "airport_code": "TEZ", "airport_name": "Salonibari Airport", "city": "Tezpur", "gate_no": 4 },
  { "airport_code": "TRZ", "airport_name": "Tiruchirappalli International Airport", "city": "Tiruchirappalli", "gate_no": 7 },
  { "airport_code": "TIR", "airport_name": "Tirupati Airport", "city": "Tirupati", "gate_no": 5 },
  { "airport_code": "UDR", "airport_name": "Maharana Pratap Airport", "city": "Udaipur", "gate_no": 9 },
  { "airport_code": "VGA", "airport_name": "Vijayawada Airport", "city": "Vijayawada", "gate_no": 6 },
  { "airport_code": "VTZ", "airport_name": "Visakhapatnam Airport", "city": "Visakhapatnam", "gate_no": 13 }
]